rcvpapi/__init__.py
rcvpapi/rcvpapi.py
rcvpapi-1.6.4.dist-info/LICENSE
rcvpapi-1.6.4.dist-info/METADATA
rcvpapi-1.6.4.dist-info/WHEEL
rcvpapi-1.6.4.dist-info/top_level.txt
rcvpapi-1.6.4.dist-info/RECORD
