Metadata-Version: 2.1
Name: rcvpapi
Version: 1.6.4
Summary: Module to interact with Arista CloudVision
Home-page: https://github.com/networkRob/rcvpapi
Author: Rob Martin
Author-email: rjmarti88@icloud.com
License: UNKNOWN
Platform: UNKNOWN
Classifier: Programming Language :: Python :: 2
Classifier: Programming Language :: Python :: 2.7
Classifier: Programming Language :: Python :: 3
Classifier: Intended Audience :: Developers
Classifier: Intended Audience :: System Administrators
Classifier: Operating System :: OS Independent
Classifier: Topic :: Software Development :: Libraries
Classifier: Topic :: Software Development :: Libraries :: Python Modules
Classifier: Topic :: System :: Networking
Requires-Dist: requests
